gptt/__init__.py
gptt/__main__.py
gptt/timetables.py
gptt/templates/__init__.py
gptt/templates/default_html_template.html
gptt-0.1.1.dist-info/LICENSE
gptt-0.1.1.dist-info/METADATA
gptt-0.1.1.dist-info/WHEEL
gptt-0.1.1.dist-info/entry_points.txt
gptt-0.1.1.dist-info/top_level.txt
gptt-0.1.1.dist-info/RECORD
