Metadata-Version: 2.1
Name: gptt
Version: 0.1.1
Summary: Download organized timetable information from the Google Directions API Transit mode for pretty output
Home-page: https://github.com/andrashann/gptt
Author: András Hann
Author-email: dev@hann.io
License: Apache License 2.0
Platform: UNKNOWN
Classifier: Development Status :: 4 - Beta
Classifier: Programming Language :: Python :: 3
Classifier: Environment :: Console
Classifier: License :: OSI Approved :: Apache Software License
Classifier: Topic :: Scientific/Engineering :: GIS
Classifier: Topic :: Utilities
Requires-Dist: requests
Requires-Dist: Jinja2
